huaweicloudsdkesw/__init__.py
huaweicloudsdkesw/v3/__init__.py
huaweicloudsdkesw/v3/esw_async_client.py
huaweicloudsdkesw/v3/esw_client.py
huaweicloudsdkesw/v3/model/__init__.py
huaweicloudsdkesw/v3/model/availability_zone.py
huaweicloudsdkesw/v3/model/availability_zones.py
huaweicloudsdkesw/v3/model/bind_vport_request.py
huaweicloudsdkesw/v3/model/bind_vport_request_body.py
huaweicloudsdkesw/v3/model/bind_vport_response.py
huaweicloudsdkesw/v3/model/connection.py
huaweicloudsdkesw/v3/model/create_connection_option.py
huaweicloudsdkesw/v3/model/create_connection_request.py
huaweicloudsdkesw/v3/model/create_connection_request_body.py
huaweicloudsdkesw/v3/model/create_connection_response.py
huaweicloudsdkesw/v3/model/create_instance_request.py
huaweicloudsdkesw/v3/model/create_instance_response.py
huaweicloudsdkesw/v3/model/create_post_paid_instance_request_body.py
huaweicloudsdkesw/v3/model/create_postpaid_instance_option.py
huaweicloudsdkesw/v3/model/delete_connection_request.py
huaweicloudsdkesw/v3/model/delete_connection_response.py
huaweicloudsdkesw/v3/model/delete_instance_request.py
huaweicloudsdkesw/v3/model/delete_instance_response.py
huaweicloudsdkesw/v3/model/flavor.py
huaweicloudsdkesw/v3/model/instance.py
huaweicloudsdkesw/v3/model/job.py
huaweicloudsdkesw/v3/model/list_availability_zones_request.py
huaweicloudsdkesw/v3/model/list_availability_zones_response.py
huaweicloudsdkesw/v3/model/list_connections_all_instances_request.py
huaweicloudsdkesw/v3/model/list_connections_all_instances_response.py
huaweicloudsdkesw/v3/model/list_connections_request.py
huaweicloudsdkesw/v3/model/list_connections_response.py
huaweicloudsdkesw/v3/model/list_flavors_request.py
huaweicloudsdkesw/v3/model/list_flavors_response.py
huaweicloudsdkesw/v3/model/list_instances_request.py
huaweicloudsdkesw/v3/model/list_instances_response.py
huaweicloudsdkesw/v3/model/list_quotas_request.py
huaweicloudsdkesw/v3/model/list_quotas_response.py
huaweicloudsdkesw-3.1.184.dist-info/METADATA
huaweicloudsdkesw-3.1.184.dist-info/WHEEL
huaweicloudsdkesw-3.1.184.dist-info/licenses/LICENSE
huaweicloudsdkesw-3.1.184.dist-info/RECORD
